ups_0auth_client_credentials/__init__.py
ups_0auth_client_credentials/sdk.py
ups_0auth_client_credentials/hooks/__init__.py
ups_0auth_client_credentials/hooks/hook.py
ups_0auth_client_credentials/models/__init__.py
ups_0auth_client_credentials/models/base.py
ups_0auth_client_credentials/models/create_token_request.py
ups_0auth_client_credentials/models/token_success_response.py
ups_0auth_client_credentials/models/utils/cast_models.py
ups_0auth_client_credentials/models/utils/json_map.py
ups_0auth_client_credentials/net/__init__.py
ups_0auth_client_credentials/net/environment/__init__.py
ups_0auth_client_credentials/net/environment/environment.py
ups_0auth_client_credentials/net/headers/__init__.py
ups_0auth_client_credentials/net/headers/base_header.py
ups_0auth_client_credentials/net/headers/basic_auth.py
ups_0auth_client_credentials/net/request_chain/__init__.py
ups_0auth_client_credentials/net/request_chain/request_chain.py
ups_0auth_client_credentials/net/request_chain/handlers/__init__.py
ups_0auth_client_credentials/net/request_chain/handlers/base_handler.py
ups_0auth_client_credentials/net/request_chain/handlers/hook_handler.py
ups_0auth_client_credentials/net/request_chain/handlers/http_handler.py
ups_0auth_client_credentials/net/request_chain/handlers/retry_handler.py
ups_0auth_client_credentials/net/transport/__init__.py
ups_0auth_client_credentials/net/transport/request.py
ups_0auth_client_credentials/net/transport/request_error.py
ups_0auth_client_credentials/net/transport/response.py
ups_0auth_client_credentials/net/transport/serializer.py
ups_0auth_client_credentials/net/transport/utils.py
ups_0auth_client_credentials/services/__init__.py
ups_0auth_client_credentials/services/security.py
ups_0auth_client_credentials/services/utils/base_service.py
ups_0auth_client_credentials/services/utils/default_headers.py
ups_0auth_client_credentials/services/utils/validator.py
ups_0auth_client_credentials-1.0.0.dist-info/LICENSE
ups_0auth_client_credentials-1.0.0.dist-info/METADATA
ups_0auth_client_credentials-1.0.0.dist-info/WHEEL
ups_0auth_client_credentials-1.0.0.dist-info/top_level.txt
ups_0auth_client_credentials-1.0.0.dist-info/RECORD
