Metadata-Version: 2.1
Name: ups-0auth-client-credentials
Version: 1.0.0
Summary: The UPS OAuth Client Credentials API helps retrieve an OAuth Bearer token when the integration owner is also the UPS shipper.
License: MIT
Requires-Python: >=3.7
License-File: LICENSE
Requires-Dist: requests >=2.31.0
